{
    "version": "0.2.0",
    "configurations": [
        {
            "name": "PhotoItemer1 (debug)",
            "request": "launch",
            "type": "dart",
            "program": "lib/main.dart",
            "args": [
                "--debug"
            ]
        },
        {
            "name": "PhotoItemer1 (profile)",
            "request": "launch",
            "type": "dart",
            "flutterMode": "profile",
            "program": "lib/main.dart"
        },
        {
            "name": "PhotoItemer1 (release)",
            "request": "launch",
            "type": "dart",
            "flutterMode": "release",
            "program": "lib/main.dart"
        },
        {
            "name": "PhotoItemer1 (Flutter iPhone Akr se)",
            "request": "launch",
            "type": "dart",
            "program": "lib/main.dart",
            "deviceId": "iPhone Akr se"
        }
    ]
}